tellus_traveler/__init__.py
tellus_traveler/http_client.py
tellus_traveler/api/__init__.py
tellus_traveler/api/_datasets.py
tellus_traveler/api/_files.py
tellus_traveler/api/_scenes.py
tellus_traveler/api/_thumbnails.py
tellus_traveler/models/__init__.py
tellus_traveler/models/_file.py
tellus_traveler/models/_scene.py
tellus_traveler/models/_scene_search.py
tellus_traveler-0.3.0.dist-info/METADATA
tellus_traveler-0.3.0.dist-info/WHEEL
tellus_traveler-0.3.0.dist-info/licenses/LICENSE
tellus_traveler-0.3.0.dist-info/RECORD
