Metadata-Version: 2.1
Name: tellus-traveler
Version: 0.3.0
Summary: Client for Tellus Traveler API
Project-URL: homepage, https://github.com/sankichi92/tellus-traveler-python
Project-URL: documentation, https://tellus-traveler.readthedocs.io
Project-URL: repository, https://github.com/sankichi92/tellus-traveler-python.git
Project-URL: changelog, https://github.com/sankichi92/tellus-traveler-python/blob/main/CHANGELOG.md
Author-email: Takahiro Miyoshi <takahiro-miyoshi@sankichi.net>
License-Expression: MIT
License-File: LICENSE
Requires-Python: >=3.10
Requires-Dist: requests>=2.31.0
